devutils/__init__.py
devutils/utils.py
devutils/tests/__init__.py
devutils/tests/test_devutils.py
devutils/tests/test_module/__init__.py
devutils/tests/test_module/test_module.py
devutils-0.0.2.dist-info/METADATA
devutils-0.0.2.dist-info/WHEEL
devutils-0.0.2.dist-info/top_level.txt
devutils-0.0.2.dist-info/RECORD
