Metadata-Version: 2.1
Name: devutils
Version: 0.0.2
Summary: various utils
Home-page: https://github.com/usuyama/devutils
Author: Naoto Usuyama
Author-email: usuyama.naoto@gmail.com
License: UNKNOWN
Platform: UNKNOWN
